pyeventick
