Metadata-Version: 1.0
Name: pyeventick
Version: 0.2
Summary: Simple integrate of API eventick.com.br with python
Home-page: https://github.com/hudsonbrendon/pyeventick
Author: Hudson Brendon
Author-email: contato.hudsonbrendon@gmail.com
License: MIT
Platform: UNKNOWN
